pyJarves/__init__.py
pyJarves/__main__.py
pyJarves/configs.py
pyJarves/exceptions.py
pyJarves/loader.py
pyJarves/version.py
pyJarves/_misc/__init__.py
pyJarves/_misc/_assistant.py
pyJarves/_misc/_decorators.py
pyJarves/_misc/_supporter.py
pyJarves/_misc/_wrappers.py
pyJarves/dB/__init__.py
pyJarves/dB/_core.py
pyJarves/dB/afk_db.py
pyJarves/dB/antiflood_db.py
pyJarves/dB/asst_fns.py
pyJarves/dB/asstcmd_db.py
pyJarves/dB/autoban_db.py
pyJarves/dB/blacklist_chat_db.py
pyJarves/dB/blacklist_db.py
pyJarves/dB/botchat_db.py
pyJarves/dB/broadcast_db.py
pyJarves/dB/ch_db.py
pyJarves/dB/dnd_db.py
pyJarves/dB/echo_db.py
pyJarves/dB/filestore_db.py
pyJarves/dB/filter_db.py
pyJarves/dB/forcesub_db.py
pyJarves/dB/gban_mute_db.py
pyJarves/dB/gcast_blacklist_db.py
pyJarves/dB/greetings_db.py
pyJarves/dB/logusers_db.py
pyJarves/dB/mute_db.py
pyJarves/dB/night_db.py
pyJarves/dB/notes_db.py
pyJarves/dB/nsfw_db.py
pyJarves/dB/pmpermit_db.py
pyJarves/dB/snips_db.py
pyJarves/dB/vc_sudos.py
pyJarves/dB/warn_db.py
pyJarves/fns/FastTelethon.py
pyJarves/fns/__init__.py
pyJarves/fns/admins.py
pyJarves/fns/executor.py
pyJarves/fns/gDrive.py
pyJarves/fns/google_image.py
pyJarves/fns/helper.py
pyJarves/fns/info.py
pyJarves/fns/misc.py
pyJarves/fns/tools.py
pyJarves/fns/ytdl.py
pyJarves/startup/BaseClient.py
pyJarves/startup/__init__.py
pyJarves/startup/_database.py
pyJarves/startup/_extra.py
pyJarves/startup/connections.py
pyJarves/startup/funcs.py
pyJarves/startup/loader.py
pyJarves/startup/utils.py
pyjarves-0.0.1.dist-info/METADATA
pyjarves-0.0.1.dist-info/WHEEL
pyjarves-0.0.1.dist-info/licenses/LICENSE
pyjarves-0.0.1.dist-info/RECORD
