Metadata-Version: 2.1
Name: pyJarves
Version: 0.0.1
Summary: Jarves is a powerfull telegram userbot
Project-URL: Telegram, https://t.me/Falcon_hacks
Author-email: MrCode403 <jagdeepsekhon101@gmail.com>
Classifier: Programming Language :: Python :: 3
